owlutils/__init__.py
owlutils/parsing.py
owlutils-0.1.0.dist-info/LICENSE
owlutils-0.1.0.dist-info/WHEEL
owlutils-0.1.0.dist-info/METADATA
owlutils-0.1.0.dist-info/RECORD
