Metadata-Version: 2.1
Name: owlutils
Version: 0.1.0
Summary: Common utils used across owl company web apps
Home-page: https://github.com/shashankkr9/owlutils
Author: Shashank Kumar
Author-email: me@shashankkumar.com
Requires-Python: >=3.7
Classifier: License :: OSI Approved :: MIT License
Classifier: Programming Language :: Python :: 3
